scrapy_jsonschema/__init__.py
scrapy_jsonschema/draft.py
scrapy_jsonschema/item.py
scrapy_jsonschema/pipeline.py
scrapy_jsonschema-0.5.0.dist-info/LICENSE
scrapy_jsonschema-0.5.0.dist-info/METADATA
scrapy_jsonschema-0.5.0.dist-info/WHEEL
scrapy_jsonschema-0.5.0.dist-info/top_level.txt
scrapy_jsonschema-0.5.0.dist-info/RECORD
