Metadata-Version: 2.1
Name: scrapy-jsonschema
Version: 0.5.0
Summary: Scrapy schema validation pipeline and Item builder using JSON Schema
Home-page: http://github.com/scrapy-plugins/scrapy-jsonschema
Author: Zyte
Author-email: opensource@zyte.com
License: BSD
Platform: Any
Classifier: Development Status :: 4 - Beta
Classifier: License :: OSI Approved :: BSD License
Classifier: Operating System :: OS Independent
Classifier: Programming Language :: Python
Classifier: Programming Language :: Python :: 3
Classifier: Programming Language :: Python :: 3.5
Classifier: Programming Language :: Python :: 3.6
Classifier: Programming Language :: Python :: 3.7
Classifier: Programming Language :: Python :: 3.8
Requires-Dist: scrapy
Requires-Dist: jsonschema[format]
